Metadata-Version: 2.1
Name: probstat-probability
Version: 1.1
Summary: Gaussian and Binomial distributions
Home-page: UNKNOWN
Author: Tayyab Khan
Author-email: tayyabkhan298@gmail.com
License: UNKNOWN
Platform: UNKNOWN
